django_anti_crawler/__init__.py
django_anti_crawler/apps.py
django_anti_crawler/middlewares.py
django_anti_crawler-0.5.dist-info/LICENSE
django_anti_crawler-0.5.dist-info/METADATA
django_anti_crawler-0.5.dist-info/WHEEL
django_anti_crawler-0.5.dist-info/top_level.txt
django_anti_crawler-0.5.dist-info/RECORD
