Metadata-Version: 2.1
Name: django-anti-crawler
Version: 0.5
Summary: A light weight anti crawler app for Django.
Home-page: https://github.com/iam-mhaseeb/Djano-Anti-Crawler
Author: Muhammad Haseeb
Author-email: haseeb.emailbox@gmail.com
License: MIT
Keywords: python,django,anti_crawler
Platform: UNKNOWN
